jp_birthday/__init__.py
jp_birthday/admin.py
jp_birthday/eras.py
jp_birthday/fields.py
jp_birthday/managers.py
jp_birthday/models.py
jp_birthday/management/commands/__init__.py
jp_birthday/management/commands/jp_birthday.py
django_jp_birthday-0.8.0.dist-info/AUTHORS.rst
django_jp_birthday-0.8.0.dist-info/LICENSE
django_jp_birthday-0.8.0.dist-info/METADATA
django_jp_birthday-0.8.0.dist-info/WHEEL
django_jp_birthday-0.8.0.dist-info/entry_points.txt
django_jp_birthday-0.8.0.dist-info/top_level.txt
django_jp_birthday-0.8.0.dist-info/RECORD
