Metadata-Version: 2.1
Name: django-jp-birthday
Version: 0.8.0
Summary: Django model for Japanese birthday.
Home-page: https://github.com/shimakaze-git/django-jp-birthday
Author: shimakaze-git
Author-email: shimakaze.soft+github@googlemail.com
License: MIT license
Keywords: django_jp_birthday django birthday era
Platform: UNKNOWN
Classifier: Development Status :: 2 - Pre-Alpha
Classifier: Framework :: Django
Classifier: Intended Audience :: Developers
Classifier: License :: OSI Approved :: MIT License
Classifier: Operating System :: OS Independent
Classifier: Programming Language :: Python
Classifier: Programming Language :: Python :: 3
Classifier: Programming Language :: Python :: 3.6
Classifier: Programming Language :: Python :: 3.7
Classifier: Programming Language :: Python :: 3.8
Classifier: Programming Language :: Python :: 3.9
Classifier: Programming Language :: Python :: 3.10
Classifier: Framework :: Django
Classifier: Framework :: Django :: 2.2
Classifier: Framework :: Django :: 3.1
Classifier: Framework :: Django :: 3.2
Classifier: Framework :: Django :: 4.0
Requires-Python: >=3.6
Requires-Dist: importlib-metadata (==4.2.0)
Requires-Dist: jeraconv (==0.2.1)
Requires-Dist: jaconv (==0.3)
